krest.py
krest-1.3.2.dist-info/AUTHORS.md
krest-1.3.2.dist-info/LICENSE
krest-1.3.2.dist-info/METADATA
krest-1.3.2.dist-info/WHEEL
krest-1.3.2.dist-info/top_level.txt
krest-1.3.2.dist-info/RECORD
