Metadata-Version: 2.1
Name: krest
Version: 1.3.2
Summary: The Kaminario REST (krest) is a client library that provides ORM like interface for working with Kaminario K2 REST API
Home-page: https://github.com/Kaminario/krest
Maintainer: Zaar Hai
Maintainer-email: haizaar@haizaar.com
License: Apache 2.0
Download-URL: https://github.com/Kaminario/krest/releases
Platform: UNKNOWN
Classifier: Development Status :: 5 - Production/Stable
Classifier: Intended Audience :: Developers
Classifier: Natural Language :: English
Classifier: License :: OSI Approved :: Apache Software License
Classifier: Programming Language :: Python
Classifier: Programming Language :: Python :: 2.6
Classifier: Programming Language :: Python :: 2.7
Classifier: Programming Language :: Python :: 3.4
Requires-Dist: requests (>=2.0.0)
